balinese_textpreprocessor/TextPreprocessor.py
balinese_textpreprocessor/__init__.py
balinese_textpreprocessor/utils.py
balinese_textpreprocessor/balinese_lemmatization/Lemmatization.py
balinese_textpreprocessor/balinese_lemmatization/LemmatizationRules.py
balinese_textpreprocessor/balinese_lemmatization/__init__.py
balinese_textpreprocessor/data/__init__.py
balinese_textpreprocessor/data/lemmatization/__init__.py
balinese_textpreprocessor/data/normalizedwords/__init__.py
balinese_textpreprocessor/data/stopwords/__init__.py
balipkg_textpreprocessor-1.1.3.dist-info/LICENSE
balipkg_textpreprocessor-1.1.3.dist-info/METADATA
balipkg_textpreprocessor-1.1.3.dist-info/WHEEL
balipkg_textpreprocessor-1.1.3.dist-info/top_level.txt
balipkg_textpreprocessor-1.1.3.dist-info/RECORD
