Metadata-Version: 2.1
Name: balipkg-textpreprocessor
Version: 1.1.3
Summary: A Python package for Balinese Text Preprocessing
Home-page: UNKNOWN
Author: I Made Satria Bimantara
Author-email: satriabimantara.md@gmail.com
License: UNKNOWN
Keywords: Balinese,NLP,Text Preprocessing,Text Analysis
Platform: UNKNOWN
Classifier: Development Status :: 3 - Alpha
Classifier: Intended Audience :: Developers
Classifier: Intended Audience :: Science/Research
Classifier: License :: OSI Approved :: MIT License
Classifier: Programming Language :: Python :: 3
Classifier: Programming Language :: Python :: 3.7
Classifier: Programming Language :: Python :: 3.8
Classifier: Operating System :: OS Independent
Classifier: Natural Language :: Indonesian
Classifier: Topic :: Text Processing :: Linguistic
Classifier: Topic :: Scientific/Engineering :: Artificial Intelligence
Requires-Python: >=3.8
Requires-Dist: pandas==1.5.3
Requires-Dist: numpy==1.24.2
Requires-Dist: balinese-library==0.0.7
Requires-Dist: nltk==3.9.1
Requires-Dist: openpyxl==3.1.0
